channels_rpc/__init__.py
channels_rpc/apps.py
channels_rpc/async_json_rpc_websocket_consumer.py
channels_rpc/async_rpc_base.py
channels_rpc/config.py
channels_rpc/context.py
channels_rpc/decorators.py
channels_rpc/exceptions.py
channels_rpc/limits.py
channels_rpc/logs.py
channels_rpc/middleware.py
channels_rpc/protocols.py
channels_rpc/registry.py
channels_rpc/rpc_base.py
channels_rpc/signals.py
channels_rpc/utils.py
channels_rpc/validation.py
channels_rpc-1.0.1.dist-info/LICENSE
channels_rpc-1.0.1.dist-info/METADATA
channels_rpc-1.0.1.dist-info/WHEEL
channels_rpc-1.0.1.dist-info/RECORD
