Metadata-Version: 2.3
Name: channels-rpc
Version: 1.0.1
Summary: JSON-RPC implementation for Django's channels library.
Author: Zvi Baratz
Author-email: zvi.baratz@quantivly.com
Requires-Python: >=3.10
Classifier: Programming Language :: Python :: 3
Classifier: Programming Language :: Python :: 3.10
Classifier: Programming Language :: Python :: 3.11
Classifier: Programming Language :: Python :: 3.12
Classifier: Programming Language :: Python :: 3.13
Requires-Dist: channels (>=4.0.0,<5.0.0)
Requires-Dist: django (>=4.2.6)
